LICENSE
MANIFEST.in
README.rst
setup.py
django_idmapper.egg-info/PKG-INFO
django_idmapper.egg-info/SOURCES.txt
django_idmapper.egg-info/dependency_links.txt
django_idmapper.egg-info/requires.txt
django_idmapper.egg-info/top_level.txt
idmapper/__init__.py
idmapper/base.py
idmapper/manager.py
idmapper/models.py
idmapper/tests.py