Metadata-Version: 1.0
Name: django-idmapper
Version: 0.2
Summary: An identify mapper for the Django ORM
Home-page: http://github.com/dcramer/django-idmapper
Author: David Cramer
Author-email: dcramer@gmail.com
License: UNKNOWN
Platform: UNKNOWN
